colour_demosaicing/__init__.py
colour_demosaicing/py.typed
colour_demosaicing/bayer/__init__.py
colour_demosaicing/bayer/masks.py
colour_demosaicing/bayer/mosaicing.py
colour_demosaicing/bayer/demosaicing/__init__.py
colour_demosaicing/bayer/demosaicing/bilinear.py
colour_demosaicing/bayer/demosaicing/malvar2004.py
colour_demosaicing/bayer/demosaicing/menon2007.py
colour_demosaicing/bayer/demosaicing/tests/__init__.py
colour_demosaicing/bayer/demosaicing/tests/test_bilinear.py
colour_demosaicing/bayer/demosaicing/tests/test_malvar2004.py
colour_demosaicing/bayer/demosaicing/tests/test_menon2007.py
colour_demosaicing/bayer/tests/__init__.py
colour_demosaicing/bayer/tests/test_masks.py
colour_demosaicing/bayer/tests/test_mosaicing.py
colour_demosaicing/examples/examples_bayer.ipynb
colour_demosaicing/resources/colour-demosaicing-examples-datasets/.git
colour_demosaicing/resources/colour-demosaicing-tests-datasets/.git
colour_demosaicing-0.2.7.dist-info/METADATA
colour_demosaicing-0.2.7.dist-info/WHEEL
colour_demosaicing-0.2.7.dist-info/licenses/LICENSE
colour_demosaicing-0.2.7.dist-info/RECORD
