Metadata-Version: 2.4
Name: colour-demosaicing
Version: 0.2.7
Summary: CFA (Colour Filter Array) Demosaicing Algorithms for Python
Project-URL: Homepage, https://www.colour-science.org
Project-URL: Documentation, https://colour-demosaicing.readthedocs.org
Project-URL: Repository, https://github.com/colour-science/colour-demosaicing
Project-URL: Issues, https://github.com/colour-science/colour-demosaicing/issues
Project-URL: Changelog, https://github.com/colour-science/colour-demosaicing/releases
Author-email: Colour Developers <colour-developers@colour-science.org>
Maintainer-email: Colour Developers <colour-developers@colour-science.org>
License: BSD-3-Clause
License-File: LICENSE
Keywords: bayer,cfa,color,color-science,color-space,color-spaces,colorspace,colorspaces,colour,colour-science,colour-space,colour-spaces,colourspace,colourspaces,de-mosaicing,debayering,demosaicing,demosaicking,python,raw
Classifier: Development Status :: 3 - Alpha
Classifier: Environment :: Console
Classifier: Intended Audience :: Developers
Classifier: Intended Audience :: Science/Research
Classifier: License :: OSI Approved
Classifier: Natural Language :: English
Classifier: Operating System :: OS Independent
Classifier: Programming Language :: Python :: 3
Classifier: Topic :: Scientific/Engineering
Classifier: Topic :: Software Development
Requires-Python: <3.15,>=3.11
Requires-Dist: colour-science>=0.4.5
Requires-Dist: imageio<3,>=2
Requires-Dist: numpy<3,>=2.0.0
Requires-Dist: scipy<2,>=1.13.0
Requires-Dist: typing-extensions<5,>=4
Provides-Extra: docs
Requires-Dist: biblib-simple; extra == 'docs'
Requires-Dist: pydata-sphinx-theme; extra == 'docs'
Requires-Dist: restructuredtext-lint; extra == 'docs'
Requires-Dist: sphinx; extra == 'docs'
Requires-Dist: sphinxcontrib-bibtex; extra == 'docs'
Provides-Extra: optional
Requires-Dist: imageio<3,>=2; extra == 'optional'
Requires-Dist: matplotlib>=3.9; extra == 'optional'
Requires-Dist: openimageio<4,>=3; extra == 'optional'
